adafruit_rtttl.py
adafruit_circuitpython_rtttl-2.4.27.dist-info/licenses/LICENSE
adafruit_circuitpython_rtttl-2.4.27.dist-info/METADATA
adafruit_circuitpython_rtttl-2.4.27.dist-info/WHEEL
adafruit_circuitpython_rtttl-2.4.27.dist-info/top_level.txt
adafruit_circuitpython_rtttl-2.4.27.dist-info/RECORD
