Metadata-Version: 2.4
Name: adafruit-circuitpython-rtttl
Version: 2.4.27
Summary: CircuitPython library for playing RTTTL melodies.
Author-email: Adafruit Industries <circuitpython@adafruit.com>
License: MIT
Project-URL: Homepage, https://github.com/adafruit/Adafruit_CircuitPython_RTTTL
Keywords: adafruit,rtttl,tones,melodies,hardware,micropython,circuitpython
Classifier: Intended Audience :: Developers
Classifier: Topic :: Software Development :: Libraries
Classifier: Topic :: Software Development :: Embedded Systems
Classifier: Topic :: System :: Hardware
Classifier: License :: OSI Approved :: MIT License
Classifier: Programming Language :: Python :: 3
License-File: LICENSE
Requires-Dist: Adafruit-Blinka
Requires-Dist: adafruit-circuitpython-waveform
Provides-Extra: optional
Dynamic: license-file
